python_wpapi/__init__.py
python_wpapi/errors.py
python_wpapi/python_wpapi.py
python_wpapi-0.3.1.dist-info/DESCRIPTION.rst
python_wpapi-0.3.1.dist-info/METADATA
python_wpapi-0.3.1.dist-info/RECORD
python_wpapi-0.3.1.dist-info/WHEEL
python_wpapi-0.3.1.dist-info/metadata.json
python_wpapi-0.3.1.dist-info/top_level.txt
