Metadata-Version: 2.0
Name: python-wpapi
Version: 0.3.1
Summary: Simple wrapper around the Wordpress REST API
Home-page: https://github.com/Lobosque/python_wpapi
Author: Lucas Lobosque
Author-email: lucas.lobosque@contentools.com
License: MIT license
Keywords: python_wpapi
Platform: UNKNOWN
Classifier: Development Status :: 2 - Pre-Alpha
Classifier: Intended Audience :: Developers
Classifier: License :: OSI Approved :: MIT License
Classifier: Natural Language :: English
Classifier: Programming Language :: Python :: 2
Classifier: Programming Language :: Python :: 2.6
Classifier: Programming Language :: Python :: 2.7
Classifier: Programming Language :: Python :: 3
Classifier: Programming Language :: Python :: 3.3
Classifier: Programming Language :: Python :: 3.4
Classifier: Programming Language :: Python :: 3.5
Requires-Dist: requests
